crimson/copilot_init_client/__init__.py
crimson/copilot_init_client/client.py
crimson_copilot_init_client-0.1.0.dist-info/LICENSE
crimson_copilot_init_client-0.1.0.dist-info/METADATA
crimson_copilot_init_client-0.1.0.dist-info/WHEEL
crimson_copilot_init_client-0.1.0.dist-info/top_level.txt
crimson_copilot_init_client-0.1.0.dist-info/RECORD
